semantic_release/__init__.py
semantic_release/__main__.py
semantic_release/cfg_loader.py
semantic_release/changelog/__init__.py
semantic_release/changelog/changelog.py
semantic_release/changelog/compare.py
semantic_release/changelog/handlers.py
semantic_release/ci_checks.py
semantic_release/cli.py
semantic_release/defaults.cfg
semantic_release/dist.py
semantic_release/errors.py
semantic_release/helpers.py
semantic_release/history/__init__.py
semantic_release/history/grouping.py
semantic_release/history/logs.py
semantic_release/history/parser_angular.py
semantic_release/history/parser_emoji.py
semantic_release/history/parser_gitmoji/__init__.py
semantic_release/history/parser_gitmoji/data.py
semantic_release/history/parser_gitmoji/parser_gitmojis.py
semantic_release/history/parser_helpers.py
semantic_release/history/parser_scipy.py
semantic_release/history/parser_tag.py
semantic_release/history/processing.py
semantic_release/hvcs.py
semantic_release/repository.py
semantic_release/settings.py
semantic_release/templates/gitmoji_template.tpl
semantic_release/templates/template.tpl
semantic_release/templates/with_sections_template.tpl
semantic_release/vcs_helpers.py
project_semantic_release-1.0.3.dist-info/entry_points.txt
project_semantic_release-1.0.3.dist-info/LICENSE
project_semantic_release-1.0.3.dist-info/WHEEL
project_semantic_release-1.0.3.dist-info/METADATA
project_semantic_release-1.0.3.dist-info/RECORD
